stats_estimator/Binomialdistribution.py
stats_estimator/Binomialdistribution_challenge.py
stats_estimator/Gaussiandistribution.py
stats_estimator/Generaldistribution.py
stats_estimator/__init__.py
stats_estimator/test.py
stats_estimator-0.0.5.dist-info/METADATA
stats_estimator-0.0.5.dist-info/WHEEL
stats_estimator-0.0.5.dist-info/top_level.txt
stats_estimator-0.0.5.dist-info/RECORD
