Metadata-Version: 2.1
Name: stats-estimator
Version: 0.0.5
Summary: Files to get values of gaussian and binomial distribution
Home-page: UNKNOWN
Author: irahul
Author-email: UNKNOWN
License: UNKNOWN
Platform: UNKNOWN
